Metadata-Version: 2.1
Name: dataproc-templates
Version: 0.0.1
Summary: Dataproc templates written in Python
Home-page: https://github.com/GoogleCloudPlatform/dataproc-templates
License: UNKNOWN
Platform: UNKNOWN
